termites/__init__.py
termites/cache.py
termites/generate.py
termites/main.py
termites/tools.py
termites/util.py
termites/config/config.py
termites-0.1.1.dist-info/METADATA
termites-0.1.1.dist-info/WHEEL
termites-0.1.1.dist-info/entry_points.txt
termites-0.1.1.dist-info/top_level.txt
termites-0.1.1.dist-info/RECORD
